Metadata-Version: 2.1
Name: dwll
Version: 1.0.1
Summary: My app description
Home-page: https://github.com/jimuisrael/dwll
Author: Diego Gonzalez (jimuisrael)
Author-email: dgonzalez.jim@gmail.com
License: BSD
Keywords: django acelerator,fast login,messages,configuration,rehuse
Platform: UNKNOWN
Classifier: Environment :: Web Environment
Classifier: Framework :: Django
Classifier: Framework :: Django :: 3.0
Classifier: Intended Audience :: Developers
Classifier: License :: OSI Approved :: BSD License
Classifier: Operating System :: OS Independent
Classifier: Programming Language :: Python
Classifier: Programming Language :: Python :: 3
Classifier: Programming Language :: Python :: 3 :: Only
Classifier: Programming Language :: Python :: 3.6
Classifier: Programming Language :: Python :: 3.7
Classifier: Programming Language :: Python :: 3.8
Classifier: Topic :: Internet :: WWW/HTTP
Classifier: Topic :: Internet :: WWW/HTTP :: Dynamic Content
Requires-Python: >=3.5
